pycoral/__init__.py
pycoral/pybind/_pywrap_coral.so
pycoral/pycoral/_pywrap_coral.so
pycoral_pi5-2.1.4.dist-info/METADATA
pycoral_pi5-2.1.4.dist-info/WHEEL
pycoral_pi5-2.1.4.dist-info/top_level.txt
pycoral_pi5-2.1.4.dist-info/RECORD
